reemployct_data_entry/__init__.py
reemployct_data_entry/controller_credentials.py
reemployct_data_entry/entry.py
reemployct_data_entry/entry_weeklyCertification.py
reemployct_data_entry/entry_workSearch.py
reemployct_data_entry/lib/__init__.py
reemployct_data_entry/lib/browser_control.py
reemployct_data_entry/lib/class_enum.py
reemployct_data_entry/lib/filepaths.py
reemployct_data_entry/lib/job_control.py
reemployct_data_entry/lib/stateDictionary.py
reemployct_data_entry/lib/wrangle_job_data.py
reemployct_data_entry/navigate_ReEmployCT.py
reemployct_data_entry/screenIDInfo.md
reemployct_data_entry/upgrade_check.py
reemployct_data_entry/workSearch_template.xlsx
reemployct_data_entry-2.1.2.dist-info/LICENSE
reemployct_data_entry-2.1.2.dist-info/METADATA
reemployct_data_entry-2.1.2.dist-info/WHEEL
reemployct_data_entry-2.1.2.dist-info/entry_points.txt
reemployct_data_entry-2.1.2.dist-info/RECORD
