Metadata-Version: 2.1
Name: reemployct-data-entry
Version: 2.1.2
Summary: Automated entry of job application data into Connecticut's DOL ReEmployCT portal.
Home-page: https://github.com/ariffjeff/ReEmployCT-Data-Entry
License: AGPL-3.0-only
Keywords: unemployment,benefits
Author: Ariff Jeff
Author-email: ariffjeff@icloud.com
Requires-Python: >=3.10.10,<4.0.0
Classifier: License :: OSI Approved :: GNU Affero General Public License v3
Classifier: Programming Language :: Python :: 3
Classifier: Programming Language :: Python :: 3.11
Classifier: Programming Language :: Python :: 3.12
Requires-Dist: colorama (>=0.4.6,<0.5.0)
Requires-Dist: cryptography (>=39.0.2,<40.0.0)
Requires-Dist: openpyxl (>=3.1.1,<4.0.0)
Requires-Dist: packaging (>=23.0,<24.0)
Requires-Dist: pandas (>=2.2.3,<3.0.0)
Requires-Dist: pwinput (>=1.0.2,<2.0.0)
Requires-Dist: requests (>=2.28.2,<3.0.0)
Requires-Dist: selenium (>=4.8.2,<5.0.0)
Requires-Dist: usaddress (>=0.5.10,<0.6.0)
Project-URL: Repository, https://github.com/ariffjeff/ReEmployCT-Data-Entry
